Metadata-Version: 1.0
Name: jnobless-dsnd-distributions
Version: 0.1
Summary: Gaussian, Binomial distributions
Home-page: UNKNOWN
Author: June Ho Choi
Author-email: mylegna0308@gmail.com
License: UNKNOWN
Platform: UNKNOWN
